MANIFEST.in
README.txt
setup.cfg
setup.py
collective/__init__.py
collective.oaiintercom.egg-info/PKG-INFO
collective.oaiintercom.egg-info/SOURCES.txt
collective.oaiintercom.egg-info/dependency_links.txt
collective.oaiintercom.egg-info/entry_points.txt
collective.oaiintercom.egg-info/namespace_packages.txt
collective.oaiintercom.egg-info/not-zip-safe
collective.oaiintercom.egg-info/requires.txt
collective.oaiintercom.egg-info/top_level.txt
collective/oaiintercom/README.txt
collective/oaiintercom/__init__.py
collective/oaiintercom/configure.zcml
collective/oaiintercom/interfaces.py
collective/oaiintercom/version.txt
collective/oaiintercom/browser/__init__.py
collective/oaiintercom/browser/configure.zcml
collective/oaiintercom/browser/oai.py
collective/oaiintercom/browser/oaierror.pt
collective/oaiintercom/browser/oaierror.py
collective/oaiintercom/browser/oaigetrecord.pt
collective/oaiintercom/browser/oaiidentify.pt
collective/oaiintercom/browser/oailistidentifiers.pt
collective/oaiintercom/browser/oailistmetadataformats.pt
collective/oaiintercom/browser/oailistrecords.pt
collective/oaiintercom/browser/oailistsets.pt
collective/oaiintercom/browser/oaimain.pt
collective/oaiintercom/doc/clases.dia
collective/oaiintercom/doc/doc.html
collective/oaiintercom/doc/images/classes.png
collective/oaiintercom/doc/images/response1.png
collective/oaiintercom/profiles/default/browserlayer.xml
collective/oaiintercom/profiles/default/metadata.xml
collective/oaiintercom/profiles/default/propertiestool.xml
collective/oaiintercom/tests/__init__.py
collective/oaiintercom/tests/base.py
collective/oaiintercom/tests/test_case_install.py
collective/oaiintercom/tests/test_doctests.py
docs/HISTORY.txt
docs/INSTALL.txt
docs/LICENSE.GPL
docs/LICENSE.txt