Metadata-Version: 1.0
Name: collective.oaiintercom
Version: 2.1.1
Summary: UNKNOWN
Home-page: http://plone.org/products/oaintercom
Author: Brent Lambert
Author-email: brent@enpraxis.net
License: GPL
Keywords: oai interface
Platform: UNKNOWN
Classifier: Framework :: Plone
Classifier: Programming Language :: Python
Classifier: Topic :: Software Development :: Libraries :: Python Modules
